{
  "_fv": 6,
  "_type": "recipe",
  "definition": {
    "recipeType": "Crafting",
    "xpReward": 0.0,
    "recipeRetstackSize": 1,
    "recipeShapeless": false,
    "recipeSlots": [
      {
        "value": "CUSTOM:TrihydrideIngot"
      },
      {
        "value": "CUSTOM:TrihydrideIngot"
      },
      {
        "value": ""
      },
      {
        "value": ""
      },
      {
        "value": "CUSTOM:Metalicstick"
      },
      {
        "value": ""
      },
      {
        "value": ""
      },
      {
        "value": "CUSTOM:Metalicstick"
      },
      {
        "value": ""
      }
    ],
    "recipeReturnStack": {
      "value": "CUSTOM:TrihydrideHoe"
    },
    "name": "trihydridehoerecipe",
    "namespace": "mod"
  }
}